README.md
setup.py
src/swikv4/__init__.py
src/swikv4/main.py
src/swikv4/items/__init__.py
src/swikv4/pages/__init__.py
src/swikv4/pages/swik_miniature_page.py
src/swikv4/pages/swik_page.py
src/swikv4/pdf_widgets/__init__.py
src/swikv4/renderers/__init__.py
src/swikv4/renderers/swik_renderer.py
src/swikv4/resources/__init__.py
src/swikv4/resources/resources.py
src/swikv4/scenes/__init__.py
src/swikv4/scenes/swik_scene.py
src/swikv4/support/__init__.py
src/swikv4/support/swik_utils.py
src/swikv4/toolbars/__init__.py
src/swikv4/toolbars/swik_page_navigation_toolbar.py
src/swikv4/toolbars/swik_toolbar.py
src/swikv4/toolbars/swik_zoom_toolbar.py
src/swikv4/tools/__init__.py
src/swikv4/views/__init__.py
src/swikv4/views/swik_layout_manager.py
src/swikv4/views/swik_miniature_view.py
src/swikv4/views/swik_view.py
src/swikv4/widgets/__init__.py
src/swikv4/widgets/swik_basic_widget.py
src/swikv4_minimal.egg-info/PKG-INFO
src/swikv4_minimal.egg-info/SOURCES.txt
src/swikv4_minimal.egg-info/dependency_links.txt
src/swikv4_minimal.egg-info/entry_points.txt
src/swikv4_minimal.egg-info/requires.txt
src/swikv4_minimal.egg-info/top_level.txt